webpush_channels/__init__.py
webpush_channels/utils.py
webpush_channels/tests/__init__.py
webpush_channels/tests/support.py
webpush_channels/tests/test_notification_payload_schema.py
webpush_channels/tests/test_subscription_schema.py
webpush_channels/tests/test_utils.py
webpush_channels/tests/test_views_channel.py
webpush_channels/tests/test_views_hello.py
webpush_channels/tests/test_views_subscription.py
webpush_channels/views/__init__.py
webpush_channels/views/channels.py
webpush_channels/views/subscriptions.py
webpush_channels-0.1.0.dist-info/DESCRIPTION.rst
webpush_channels-0.1.0.dist-info/METADATA
webpush_channels-0.1.0.dist-info/RECORD
webpush_channels-0.1.0.dist-info/WHEEL
webpush_channels-0.1.0.dist-info/entry_points.txt
webpush_channels-0.1.0.dist-info/metadata.json
webpush_channels-0.1.0.dist-info/top_level.txt
