Metadata-Version: 2.0
Name: webpush-channels
Version: 0.1.0
Summary: Broadcast notifications to multiple WebPush subscribers.
Home-page: https://github.com/webpush-channels/webpush-channels
Author: Mansimar Kaur
Author-email: mansimarkaur.mks@gmail.com
License: Apache License (2.0)
Keywords: webpush notifications,webpush channels
Platform: UNKNOWN
Requires-Dist: kinto[postgresql] (<6)
Requires-Dist: pywebpush (>=0.7.0)
Requires-Dist: requests (<2.13.0)
Requires-Dist: waitress
